common_python_programs/__init__.py
common_python_programs-0.1.dist-info/METADATA
common_python_programs-0.1.dist-info/WHEEL
common_python_programs-0.1.dist-info/top_level.txt
common_python_programs-0.1.dist-info/RECORD
