Metadata-Version: 2.1
Name: common-python-programs
Version: 0.1
Summary: This package was created for internal usage
Home-page: https://github.com/Saichandarreddy/common_python_programs
Author: Saichandar Reddy
Author-email: saichandarreddyt@gmail.com
License: MIT
Platform: UNKNOWN
Requires-Dist: flask
Requires-Dist: pandas
